xml_analyser/__init__.py
xml_analyser/cli.py
xml_analyser-1.3.dist-info/LICENSE
xml_analyser-1.3.dist-info/METADATA
xml_analyser-1.3.dist-info/WHEEL
xml_analyser-1.3.dist-info/entry_points.txt
xml_analyser-1.3.dist-info/top_level.txt
xml_analyser-1.3.dist-info/RECORD
