Metadata-Version: 2.1
Name: xml-analyser
Version: 1.3
Summary: Analyse the structure of an arbitrary XML file
Home-page: https://github.com/simonw/xml-analyser
Author: Simon Willison
License: Apache License, Version 2.0
Project-URL: Issues, https://github.com/simonw/xml-analyser/issues
Project-URL: CI, https://github.com/simonw/xml-analyser/actions
Project-URL: Changelog, https://github.com/simonw/xml-analyser/releases
Platform: UNKNOWN
License-File: LICENSE
Provides-Extra: test
Requires-Dist: pytest ; extra == 'test'
